{
    "satellites": ["LANDSAT-4", "LANDSAT-5", "LANDSAT-7", "LANDSAT-8", "LANDSAT-9"],
    "devices": ["TM", "ETM_PLUS", "ETM_PLUS_SR", "OLI", "OLI_TIRS", "TIRS", "OLI_SR"],
    "stations": ["USGS"],
    "products": ["lc2_b4", "lc2_b5"],
    "limit": 10,
    "bbox": null,
    "dt_from": null,
    "dt": null,
    "_valid": {
        "products": [
            "ndvi",
            "source",
            "meta",
            "fmask",
            "lc2_b1",
            "lc2_b2",
            "lc2_b3",
            "lc2_b4",
            "lc2_b5",
            "lc2_b6",
            "lc2_b7",
            "lc2_qa_l1_px",
            "lc2_qa_l1_rs",
            "lc2_ang_sen_azimuth",
            "lc2_ang_sen_zenith",
            "lc2_ang_sol_azimuth",
            "lc2_ang_sol_zenith",
            "lc2_mtl",
            "source_pan",
            "fmask_2",
            "lc2_b6_vc1",
            "lc2_b6_vc2",
            "lc2_b8",
            "meta_sr",
            "color_sst_masked",
            "color_sst",
            "source_sr",
            "lc2_b9",
            "lc2_b10",
            "lc2_b11"
        ]
    }
}